youku_upload/__init__.py
youku_upload/command.py
youku_upload/util.py
youku_upload/youku_upload.py
youku_upload-0.1.1.dist-info/LICENSE
youku_upload-0.1.1.dist-info/METADATA
youku_upload-0.1.1.dist-info/WHEEL
youku_upload-0.1.1.dist-info/entry_points.txt
youku_upload-0.1.1.dist-info/top_level.txt
youku_upload-0.1.1.dist-info/RECORD
