Metadata-Version: 2.1
Name: youku-upload
Version: 0.1.1
Summary: Upload videos to Youku from the command line
Home-page: https://github.com/DistPub/youku-upload
Author: Smite Chow
Author-email: xiaopengyou2no1@gmail.com
License: MIT
Platform: UNKNOWN
Classifier: Development Status :: 5 - Production/Stable
Classifier: Environment :: Console
Classifier: Intended Audience :: End Users/Desktop
Classifier: License :: OSI Approved :: MIT License
Classifier: Natural Language :: English
Classifier: Operating System :: OS Independent
Classifier: Programming Language :: Python
Classifier: Programming Language :: Python :: 3
Classifier: Programming Language :: Python :: 3.6
Classifier: Programming Language :: Python :: 3 :: Only
Classifier: Topic :: Internet :: WWW/HTTP
Requires-Python: >=3.6
Requires-Dist: oss2
Requires-Dist: requests
Requires-Dist: progressbar2
